zepben/cimbend/__init__.py
zepben/cimbend/exceptions.py
zepben/cimbend/util.py
zepben/cimbend/cim/__init__.py
zepben/cimbend/cim/iec61968/__init__.py
zepben/cimbend/cim/iec61968/assetinfo/__init__.py
zepben/cimbend/cim/iec61968/assetinfo/wire_info.py
zepben/cimbend/cim/iec61968/assetinfo/wire_material_kind.py
zepben/cimbend/cim/iec61968/assets/__init__.py
zepben/cimbend/cim/iec61968/assets/asset.py
zepben/cimbend/cim/iec61968/assets/asset_info.py
zepben/cimbend/cim/iec61968/assets/asset_organisation_role.py
zepben/cimbend/cim/iec61968/assets/pole.py
zepben/cimbend/cim/iec61968/assets/streetlight.py
zepben/cimbend/cim/iec61968/assets/structure.py
zepben/cimbend/cim/iec61968/common/__init__.py
zepben/cimbend/cim/iec61968/common/document.py
zepben/cimbend/cim/iec61968/common/location.py
zepben/cimbend/cim/iec61968/common/organisation.py
zepben/cimbend/cim/iec61968/common/organisation_role.py
zepben/cimbend/cim/iec61968/customers/__init__.py
zepben/cimbend/cim/iec61968/customers/customer.py
zepben/cimbend/cim/iec61968/customers/customer_agreement.py
zepben/cimbend/cim/iec61968/customers/customer_kind.py
zepben/cimbend/cim/iec61968/customers/pricing_structure.py
zepben/cimbend/cim/iec61968/customers/tariff.py
zepben/cimbend/cim/iec61968/metering/__init__.py
zepben/cimbend/cim/iec61968/metering/metering.py
zepben/cimbend/cim/iec61968/operations/__init__.py
zepben/cimbend/cim/iec61968/operations/operational_restriction.py
zepben/cimbend/cim/iec61970/__init__.py
zepben/cimbend/cim/iec61970/base/__init__.py
zepben/cimbend/cim/iec61970/base/auxiliaryequipment/__init__.py
zepben/cimbend/cim/iec61970/base/auxiliaryequipment/auxiliary_equipment.py
zepben/cimbend/cim/iec61970/base/core/__init__.py
zepben/cimbend/cim/iec61970/base/core/base_voltage.py
zepben/cimbend/cim/iec61970/base/core/conducting_equipment.py
zepben/cimbend/cim/iec61970/base/core/connectivity_node.py
zepben/cimbend/cim/iec61970/base/core/connectivity_node_container.py
zepben.cimbend-0.16.0.dist-info/LICENSE
zepben.cimbend-0.16.0.dist-info/METADATA
zepben.cimbend-0.16.0.dist-info/WHEEL
zepben.cimbend-0.16.0.dist-info/top_level.txt
zepben.cimbend-0.16.0.dist-info/RECORD
