Metadata-Version: 2.1
Name: zepben.cimbend
Version: 0.16.0
Summary: Python SDK for interacting with the Evolve platform
Home-page: https://github.com/zepben/evolve-sdk-python
Author: Kurt Greaves
Author-email: kurt.greaves@zepben.com
License: MPL 2.0
Platform: UNKNOWN
Classifier: License :: OSI Approved :: Mozilla Public License 2.0 (MPL 2.0)
Classifier: Programming Language :: Python :: 3
Classifier: Programming Language :: Python :: 3.7
Classifier: Operating System :: OS Independent
Requires-Python: >=3.7
Requires-Dist: protobuf
Requires-Dist: requests
Requires-Dist: zepben.protobuf
Requires-Dist: python-jose-cryptodome
Requires-Dist: dataclassy
Provides-Extra: test
Requires-Dist: pytest ; extra == 'test'
Requires-Dist: pytest-asyncio ; extra == 'test'
Requires-Dist: hypothesis (<6) ; extra == 'test'
